linkpreview_cli/__init__.py
linkpreview_cli-1.0.0.dist-info/licenses/LICENSE
linkpreview_cli-1.0.0.dist-info/METADATA
linkpreview_cli-1.0.0.dist-info/WHEEL
linkpreview_cli-1.0.0.dist-info/entry_points.txt
linkpreview_cli-1.0.0.dist-info/top_level.txt
linkpreview_cli-1.0.0.dist-info/RECORD
