Metadata-Version: 2.4
Name: linkpreview-cli
Version: 1.0.0
Summary: Generate beautiful link previews from any URL with smart image detection
Home-page: https://github.com/yoel-frischoff/linkpreview-cli
Author: Yoel Frischoff
Author-email: yoel.frischoff@gmail.com
Project-URL: Bug Tracker, https://github.com/yoel-frischoff/linkpreview-cli/issues
Project-URL: Documentation, https://github.com/yoel-frischoff/linkpreview-cli/wiki
Project-URL: Source, https://github.com/yoel-frischoff/linkpreview-cli
Keywords: link preview,open graph,metadata,url,social media,image generation,pdf,png
Classifier: Development Status :: 5 - Production/Stable
Classifier: Intended Audience :: Developers
Classifier: Intended Audience :: End Users/Desktop
Classifier: License :: OSI Approved :: MIT License
Classifier: Operating System :: OS Independent
Classifier: Programming Language :: Python :: 3
Classifier: Programming Language :: Python :: 3.8
Classifier: Programming Language :: Python :: 3.9
Classifier: Programming Language :: Python :: 3.10
Classifier: Programming Language :: Python :: 3.11
Classifier: Programming Language :: Python :: 3.12
Classifier: Topic :: Internet :: WWW/HTTP
Classifier: Topic :: Multimedia :: Graphics
Classifier: Topic :: Software Development :: Libraries :: Python Modules
Classifier: Topic :: Utilities
Classifier: Environment :: Console
Requires-Python: >=3.8
License-File: LICENSE
Requires-Dist: requests>=2.28.0
Requires-Dist: beautifulsoup4>=4.11.0
Requires-Dist: Pillow>=9.0.0
Requires-Dist: playwright>=1.30.0
Requires-Dist: lxml>=4.9.0
Provides-Extra: dev
Requires-Dist: pytest>=6.0; extra == "dev"
Requires-Dist: pytest-cov; extra == "dev"
Requires-Dist: black; extra == "dev"
Requires-Dist: isort; extra == "dev"
Requires-Dist: flake8; extra == "dev"
Dynamic: author
Dynamic: author-email
Dynamic: classifier
Dynamic: description
Dynamic: description-content-type
Dynamic: home-page
Dynamic: keywords
Dynamic: license-file
Dynamic: project-url
Dynamic: provides-extra
Dynamic: requires-dist
Dynamic: requires-python
Dynamic: summary
